gender_based_ml/__init__.py
gender_based_ml/get_gender.py
gender_based_ml/keras_model.h5
gender_based_ml-0.9.2.dist-info/METADATA
gender_based_ml-0.9.2.dist-info/WHEEL
gender_based_ml-0.9.2.dist-info/top_level.txt
gender_based_ml-0.9.2.dist-info/RECORD
