Metadata-Version: 2.1
Name: gender_based_ml
Version: 0.9.2
Summary: ML based project to determine the gender of a speaker in an audio file
Home-page: https://github.com/pypa/sampleproject
Author: Shruthipriya
Author-email: priya@shavik.ai
Project-URL: Bug Tracker, https://github.com/pypa/sampleproject/issues
Classifier: Programming Language :: Python :: 3
Classifier: License :: OSI Approved :: MIT License
Classifier: Operating System :: OS Independent
Requires-Python: >=3.6
Requires-Dist: tensorflow >=2.7.0
Requires-Dist: keras >=2.7.0
Requires-Dist: torch >=0.8.1
Requires-Dist: gitpython >=3.1.30
